tacotoolbox/__init__.py
tacotoolbox/_column_utils.py
tacotoolbox/_constants.py
tacotoolbox/_exceptions.py
tacotoolbox/_logging.py
tacotoolbox/_metadata.py
tacotoolbox/_progress.py
tacotoolbox/_tacollection.py
tacotoolbox/_validation.py
tacotoolbox/_virtual_zip.py
tacotoolbox/_writers/folder_writer.py
tacotoolbox/_writers/zip_writer.py
tacotoolbox/create.py
tacotoolbox/datamodel/__init__.py
tacotoolbox/datamodel/sample.py
tacotoolbox/datamodel/taco.py
tacotoolbox/datamodel/tortilla.py
tacotoolbox/docs.py
tacotoolbox/sample/__init__.py
tacotoolbox/sample/datamodel.py
tacotoolbox/sample/extensions/__init__.py
tacotoolbox/sample/extensions/geotiff_stats.py
tacotoolbox/sample/extensions/istac.py
tacotoolbox/sample/extensions/scaling.py
tacotoolbox/sample/extensions/split.py
tacotoolbox/sample/extensions/stac.py
tacotoolbox/sample/extensions/tacotiff.py
tacotoolbox/sample/validators/__init__.py
tacotoolbox/sample/validators/_base.py
tacotoolbox/sample/validators/tacotiff.py
tacotoolbox/taco/__init__.py
tacotoolbox/taco/datamodel.py
tacotoolbox/taco/extensions/labels.py
tacotoolbox/taco/extensions/opticaldata.py
tacotoolbox/taco/extensions/opticaldata_utils.py
tacotoolbox/taco/extensions/scientific.py
tacotoolbox/taco/extensions/split.py
tacotoolbox/tacocat.py
tacotoolbox/templates/collection.html
tacotoolbox/templates/collection.md
tacotoolbox/templates/map.js
tacotoolbox/templates/pit_graph.js
tacotoolbox/templates/styles.css
tacotoolbox/templates/ui-interactions.js
tacotoolbox/templates/vendor/LICENSES.txt
tacotoolbox/templates/vendor/atom-one-dark.min.css
tacotoolbox/templates/vendor/d3.min.js
tacotoolbox/templates/vendor/highlight.min.js
tacotoolbox/templates/vendor/languages/julia.min.js
tacotoolbox/templates/vendor/languages/python.min.js
tacotoolbox/templates/vendor/languages/r.min.js
tacotoolbox/templates/vendor/leaflet.min.css
tacotoolbox/templates/vendor/leaflet.min.js
tacotoolbox/tortilla/__init__.py
tacotoolbox/tortilla/data/admin/admin0.parquet
tacotoolbox-0.26.1.dist-info/METADATA
tacotoolbox-0.26.1.dist-info/WHEEL
tacotoolbox-0.26.1.dist-info/licenses/LICENSE
tacotoolbox-0.26.1.dist-info/RECORD
