Metadata-Version: 2.4
Name: tacotoolbox
Version: 0.26.1
Summary: Creation toolkit for AI-ready datasets.
License-Expression: MIT
License-File: LICENSE
Keywords: earth-observation,geospatial,machine-learning,satellite-imagery,remote-sensing,ai-ready-datasets,data-pipeline,stac
Author: Cesar Aybar
Author-email: cesar.aybar@uv.es
Requires-Python: >=3.11,<3.14
Classifier: Development Status :: 4 - Beta
Classifier: Intended Audience :: Science/Research
Classifier: License :: OSI Approved :: MIT License
Classifier: Operating System :: OS Independent
Classifier: Programming Language :: Python :: 3
Classifier: Programming Language :: Python :: 3.11
Classifier: Programming Language :: Python :: 3.12
Classifier: Programming Language :: Python :: 3.13
Classifier: Topic :: Scientific/Engineering :: Artificial Intelligence
Classifier: Topic :: Scientific/Engineering :: GIS
Classifier: Typing :: Typed
Provides-Extra: all
Provides-Extra: docs
Provides-Extra: earthengine
Provides-Extra: gdal
Provides-Extra: stats
Requires-Dist: earthengine-api (>=0.1.0) ; extra == "all"
Requires-Dist: earthengine-api (>=0.1.0) ; extra == "earthengine"
Requires-Dist: gdal (>=3.0.0) ; extra == "all"
Requires-Dist: gdal (>=3.0.0) ; extra == "gdal"
Requires-Dist: jinja2 (>=3.0.0) ; extra == "all"
Requires-Dist: jinja2 (>=3.0.0) ; extra == "docs"
Requires-Dist: markdown (>=3.0.0) ; extra == "all"
Requires-Dist: markdown (>=3.0.0) ; extra == "docs"
Requires-Dist: numpy (>=1.24) ; extra == "all"
Requires-Dist: numpy (>=1.24) ; extra == "stats"
Requires-Dist: pyarrow (>=21.0.0)
Requires-Dist: pydantic (>=2.10.3)
Requires-Dist: pyproj (>=3.7.2)
Requires-Dist: shapely (>=2.1.1)
Requires-Dist: tacozip (>=0.11.4)
Requires-Dist: tqdm (>=4.67.1)
Project-URL: Bug Tracker, https://github.com/tacofoundation/taco-toolbox/issues
Project-URL: Changelog, https://github.com/tacofoundation/taco-toolbox/releases
Project-URL: Documentation, https://tacofoundation.github.io/taco-toolbox
Project-URL: Repository, https://github.com/tacofoundation/taco-toolbox
